.gitignore
.landscape.yml
LICENSE.md
README.md
setup.cfg
setup.py
smbus2_asyncio/__init__.py
smbus2_asyncio/version.py
smbus2_asyncio.egg-info/PKG-INFO
smbus2_asyncio.egg-info/SOURCES.txt
smbus2_asyncio.egg-info/dependency_links.txt
smbus2_asyncio.egg-info/requires.txt
smbus2_asyncio.egg-info/top_level.txt