Metadata-Version: 1.1
Name: smbus2-asyncio
Version: 0.0.5
Summary: Asyncio support for SMBUS2
Home-page: http://github.com/jabdoa2/smbus2_asyncio
Author: Jan Kantert
Author-email: jan-smbus2-asyncio@kantert.net
License: MIT
Keywords: i2c,smbus,smbus2,linux
Platform: UNKNOWN
Classifier: Development Status :: 3 - Alpha
Classifier: Intended Audience :: Developers
Classifier: License :: OSI Approved :: MIT License
Classifier: Programming Language :: Python :: 3.4
Classifier: Programming Language :: Python :: 3.5
Classifier: Programming Language :: Python :: 3.6
Classifier: Programming Language :: Python :: 3.7
Classifier: Natural Language :: English
Classifier: Operating System :: POSIX :: Linux
